{
    "NPC_Aisha": {
        "Version": "1.10.1822.1",
        "Scene": {
            "Name": true,
            "SupportShaderSelect": true
        },
        "Export Directory": "C:/Users/Omer/Desktop/Silvermoon Studio/COMPANIONS GAME LAST/Companions Game Characters/09-17-24/NPC_Aisha",
        "Object": {
            "NPC_Aisha": {
                "Generation": "RL_CharacterCreator_Base_Game_G1_Divide_Eyelash_UV",
                "Physics": {
                    "Collision Shapes": {
                        "pelvis": {
                            "Capsule": {
                                "Bone Active": true,
                                "Bound Type": "Capsule",
                                "Bound Axis": "Y",
                                "Margin": 2.0,
                                "Friction": 0.05000000074505806,
                                "Elasticity": 0.5,
                                "WorldTranslate": [
                                    -5.579739570617676,
                                    2.8996238708496095,
                                    102.65424346923828
                                ],
                                "WorldRotationQ": [
                                    0.8121449947357178,
                                    0.07486160099506378,
                                    -0.10690692067146301,
                                    0.568671464920044
                                ],
                                "WorldScale": [
                                    1.0000001192092896,
                                    1.0000001192092896,
                                    1.0000001192092896
                                ],
                                "Radius": 9.339056968688965,
                                "Capsule Length": 22.12552833557129
                            },
                            "Capsule(0)": {
                                "Bone Active": true,
                                "Bound Type": "Capsule",
                                "Bound Axis": "Y",
                                "Margin": 2.0,
                                "Friction": 0.05000000074505806,
                                "Elasticity": 0.5,
                                "WorldTranslate": [
                                    5.4194159507751469,
                                    2.673738479614258,
                                    103.25411224365235
                                ],
                                "WorldRotationQ": [
                                    0.8121424317359924,
                                    -0.07487176358699799,
                                    0.1069347932934761,
                                    0.5686684846878052
                                ],
                                "WorldScale": [
                                    0.9999999403953552,
                                    1.0000001192092896,
                                    1.0000001192092896
                                ],
                                "Radius": 9.339056968688965,
                                "Capsule Length": 21.503252029418947
                            }
                        },
                        "thigh_l": {
                            "Capsule": {
                                "Bone Active": true,
                                "Bound Type": "Capsule",
                                "Bound Axis": "Y",
                                "Margin": 0.800000011920929,
                                "Friction": 0.05000000074505806,
                                "Elasticity": 0.5,
                                "WorldTranslate": [
                                    9.215192794799805,
                                    1.9592351913452149,
                                    76.09953308105469
                                ],
                                "WorldRotationQ": [
                                    -0.03083684667944908,
                                    0.7437329292297363,
                                    -0.6668881177902222,
                                    -0.03421559929847717
                                ],
                                "WorldScale": [
                                    1.0000001192092896,
                                    1.0000001192092896,
                                    1.0000001192092896
                                ],
                                "Radius": 7.741213798522949,
                                "Capsule Length": 33.47917938232422
                            }
                        },
                        "calf_l": {
                            "Capsule": {
                                "Bone Active": true,
                                "Bound Type": "Capsule",
                                "Bound Axis": "Y",
                                "Margin": 0.800000011920929,
                                "Friction": 0.05000000074505806,
                                "Elasticity": 0.5,
                                "WorldTranslate": [
                                    7.950023174285889,
                                    5.142675399780273,
                                    29.39769172668457
                                ],
                                "WorldRotationQ": [
                                    -0.006278155371546745,
                                    0.70890873670578,
                                    -0.7052425146102905,
                                    -0.006478181574493647
                                ],
                                "WorldScale": [
                                    1.000000238418579,
                                    1.000000238418579,
                                    1.000000238418579
                                ],
                                "Radius": 5.8112921714782719,
                                "Capsule Length": 33.6202507019043
                            }
                        },
                        "thigh_r": {
                            "Capsule": {
                                "Bone Active": true,
                                "Bound Type": "Capsule",
                                "Bound Axis": "Y",
                                "Margin": 0.800000011920929,
                                "Friction": 0.05000000074505806,
                                "Elasticity": 0.5,
                                "WorldTranslate": [
                                    -9.002500534057618,
                                    2.2040109634399416,
                                    73.80438232421875
                                ],
                                "WorldRotationQ": [
                                    0.030826915055513383,
                                    0.7436202168464661,
                                    -0.667013943195343,
                                    0.03422112017869949
                                ],
                                "WorldScale": [
                                    0.9999999403953552,
                                    1.0,
                                    1.0000001192092896
                                ],
                                "Radius": 7.777102470397949,
                                "Capsule Length": 38.07891845703125
                            }
                        },
                        "calf_r": {
                            "Capsule": {
                                "Bone Active": true,
                                "Bound Type": "Capsule",
                                "Bound Axis": "Y",
                                "Margin": 0.800000011920929,
                                "Friction": 0.05000000074505806,
                                "Elasticity": 0.5,
                                "WorldTranslate": [
                                    -7.9500322341918949,
                                    5.131759166717529,
                                    29.397232055664064
                                ],
                                "WorldRotationQ": [
                                    0.00625932402908802,
                                    0.7089407444000244,
                                    -0.7052106857299805,
                                    0.006462205201387405
                                ],
                                "WorldScale": [
                                    1.0000005960464478,
                                    1.0000007152557374,
                                    1.0000003576278687
                                ],
                                "Radius": 5.810446262359619,
                                "Capsule Length": 33.61426544189453
                            }
                        },
                        "spine_02": {
                            "Capsule": {
                                "Bone Active": true,
                                "Bound Type": "Capsule",
                                "Bound Axis": "Z",
                                "Margin": 2.0,
                                "Friction": 0.05000000074505806,
                                "Elasticity": 0.5,
                                "WorldTranslate": [
                                    0.00045996918925084174,
                                    1.0999881029129029,
                                    124.0649642944336
                                ],
                                "WorldRotationQ": [
                                    0.45805051922798159,
                                    0.5387042164802551,
                                    0.4580428898334503,
                                    0.538687527179718
                                ],
                                "WorldScale": [
                                    1.0000001192092896,
                                    1.0000001192092896,
                                    1.0
                                ],
                                "Radius": 11.629988670349121,
                                "Capsule Length": 6.390512466430664
                            }
                        },
                        "upperarm_l": {
                            "Capsule": {
                                "Bone Active": true,
                                "Bound Type": "Capsule",
                                "Bound Axis": "Y",
                                "Margin": 0.800000011920929,
                                "Friction": 0.05000000074505806,
                                "Elasticity": 0.5,
                                "WorldTranslate": [
                                    23.80783462524414,
                                    8.461697578430176,
                                    140.80178833007813
                                ],
                                "WorldRotationQ": [
                                    0.49779239296913149,
                                    0.5022010803222656,
                                    -0.5021371841430664,
                                    0.4978504776954651
                                ],
                                "WorldScale": [
                                    1.0000001192092896,
                                    0.9999998211860657,
                                    1.0000001192092896
                                ],
                                "Radius": 5.2370147705078129,
                                "Capsule Length": 19.877002716064454
                            }
                        },
                        "lowerarm_l": {
                            "Capsule": {
                                "Bone Active": true,
                                "Bound Type": "Capsule",
                                "Bound Axis": "Y",
                                "Margin": 0.800000011920929,
                                "Friction": 0.05000000074505806,
                                "Elasticity": 0.5,
                                "WorldTranslate": [
                                    52.18012237548828,
                                    7.901931285858154,
                                    141.8783721923828
                                ],
                                "WorldRotationQ": [
                                    -0.49873754382133486,
                                    -0.501259982585907,
                                    0.5029171705245972,
                                    -0.49706506729125979
                                ],
                                "WorldScale": [
                                    1.0000001192092896,
                                    0.9999999403953552,
                                    1.000000238418579
                                ],
                                "Radius": 4.650128364562988,
                                "Capsule Length": 19.08824348449707
                            }
                        },
                        "upperarm_r": {
                            "Capsule": {
                                "Bone Active": true,
                                "Bound Type": "Capsule",
                                "Bound Axis": "Y",
                                "Margin": 0.800000011920929,
                                "Friction": 0.05000000074505806,
                                "Elasticity": 0.5,
                                "WorldTranslate": [
                                    -23.807884216308595,
                                    8.462173461914063,
                                    140.80198669433595
                                ],
                                "WorldRotationQ": [
                                    -0.49781182408332827,
                                    0.5021756291389465,
                                    -0.5021506547927856,
                                    -0.4978431165218353
                                ],
                                "WorldScale": [
                                    1.0000004768371583,
                                    0.9999998807907105,
                                    1.0
                                ],
                                "Radius": 5.236366271972656,
                                "Capsule Length": 19.878437042236329
                            },
                            "Capsule(0)": {
                                "Bone Active": true,
                                "Bound Type": "Capsule",
                                "Bound Axis": "Y",
                                "Margin": 0.800000011920929,
                                "Friction": 0.05000000074505806,
                                "Elasticity": 0.5,
                                "WorldTranslate": [
                                    -26.559953689575197,
                                    7.899334907531738,
                                    142.03720092773438
                                ],
                                "WorldRotationQ": [
                                    -0.49781182408332827,
                                    0.5021756291389465,
                                    -0.5021506547927856,
                                    -0.4978431165218353
                                ],
                                "WorldScale": [
                                    1.0000004768371583,
                                    0.9999998807907105,
                                    1.0
                                ],
                                "Radius": 4.7389116287231449,
                                "Capsule Length": 22.378591537475587
                            }
                        },
                        "neck_01": {
                            "Capsule": {
                                "Bone Active": true,
                                "Bound Type": "Capsule",
                                "Bound Axis": "Y",
                                "Margin": 0.800000011920929,
                                "Friction": 0.05000000074505806,
                                "Elasticity": 0.5,
                                "WorldTranslate": [
                                    -0.00003525210922816768,
                                    5.520689010620117,
                                    150.8693389892578
                                ],
                                "WorldRotationQ": [
                                    0.793163537979126,
                                    -0.000020782321371370928,
                                    -0.000024057166228885764,
                                    0.6090087294578552
                                ],
                                "WorldScale": [
                                    1.0,
                                    1.0,
                                    1.0
                                ],
                                "Radius": 4.799605369567871,
                                "Capsule Length": 0.18861007690429688
                            },
                            "Capsule(0)": {
                                "Bone Active": true,
                                "Bound Type": "Capsule",
                                "Bound Axis": "Z",
                                "Margin": 0.800000011920929,
                                "Friction": 0.05000000074505806,
                                "Elasticity": 0.5,
                                "WorldTranslate": [
                                    -0.0001611123443581164,
                                    5.550013065338135,
                                    138.74264526367188
                                ],
                                "WorldRotationQ": [
                                    0.5608683228492737,
                                    0.4306195378303528,
                                    0.5608343482017517,
                                    0.43064892292022707
                                ],
                                "WorldScale": [
                                    0.9999999403953552,
                                    1.0,
                                    0.9999999403953552
                                ],
                                "Radius": 6.6594977378845219,
                                "Capsule Length": 13.492592811584473
                            },
                            "Capsule(1)": {
                                "Bone Active": true,
                                "Bound Type": "Capsule",
                                "Bound Axis": "Y",
                                "Margin": 0.800000011920929,
                                "Friction": 0.05000000074505806,
                                "Elasticity": 0.5,
                                "WorldTranslate": [
                                    -7.000361919403076,
                                    3.3883495330810549,
                                    134.6876220703125
                                ],
                                "WorldRotationQ": [
                                    0.2711974084377289,
                                    0.6530377864837647,
                                    0.27115318179130556,
                                    0.6530463695526123
                                ],
                                "WorldScale": [
                                    0.9999998807907105,
                                    0.9999998807907105,
                                    0.9999999403953552
                                ],
                                "Radius": 6.620144844055176,
                                "Capsule Length": 3.9281845092773439
                            },
                            "Capsule(2)": {
                                "Bone Active": true,
                                "Bound Type": "Capsule",
                                "Bound Axis": "Y",
                                "Margin": 0.800000011920929,
                                "Friction": 0.05000000074505806,
                                "Elasticity": 0.5,
                                "WorldTranslate": [
                                    6.999638080596924,
                                    3.3874778747558595,
                                    134.68743896484376
                                ],
                                "WorldRotationQ": [
                                    0.2711974084377289,
                                    0.6530377864837647,
                                    0.27115318179130556,
                                    0.6530463695526123
                                ],
                                "WorldScale": [
                                    0.9999998807907105,
                                    0.9999998807907105,
                                    0.9999999403953552
                                ],
                                "Radius": 6.620144844055176,
                                "Capsule Length": 3.9281845092773439
                            }
                        },
                        "head": {
                            "Capsule": {
                                "Bone Active": true,
                                "Bound Type": "Capsule",
                                "Bound Axis": "Y",
                                "Margin": 0.800000011920929,
                                "Friction": 0.05000000074505806,
                                "Elasticity": 0.5,
                                "WorldTranslate": [
                                    0.00003192509029759094,
                                    1.4946022033691407,
                                    161.37461853027345
                                ],
                                "WorldRotationQ": [
                                    0.7071053981781006,
                                    0.000005875847364222864,
                                    0.0000023808884179743474,
                                    0.7071081399917603
                                ],
                                "WorldScale": [
                                    1.0,
                                    1.000000238418579,
                                    1.000000238418579
                                ],
                                "Radius": 7.450110912322998,
                                "Capsule Length": 8.07003116607666
                            }
                        }
                    }
                },
                "Meshes": {
                    "CC_Base_Body": {
                        "Materials": {
                            "Ga_Skin_Body": {
                                "Material Type": "Pbr",
                                "MultiUV Index": 0,
                                "Two Side": true,
                                "Diffuse Color": [
                                    255.0,
                                    255.0,
                                    255.0
                                ],
                                "Ambient Color": [
                                    254.00001525878907,
                                    254.00001525878907,
                                    254.00001525878907
                                ],
                                "Specular Color": [
                                    229.5,
                                    229.5,
                                    229.5
                                ],
                                "Opacity": 1.0,
                                "Self Illumination": 0.0,
                                "Textures": {
                                    "Metallic": {
                                        "Texture Path": "",
                                        "Strength": 100.0,
                                        "Offset": [
                                            0.0,
                                            0.0
                                        ],
                                        "Tiling": [
                                            1.0,
                                            1.0
                                        ]
                                    },
                                    "Base Color": {
                                        "Texture Path": "Ga_Skin_Body_Diffuse.png",
                                        "Strength": 100.0,
                                        "Offset": [
                                            0.0,
                                            0.0
                                        ],
                                        "Tiling": [
                                            1.0,
                                            1.0
                                        ]
                                    },
                                    "Roughness": {
                                        "Texture Path": "",
                                        "Strength": 100.0,
                                        "Offset": [
                                            0.0,
                                            0.0
                                        ],
                                        "Tiling": [
                                            1.0,
                                            1.0
                                        ]
                                    },
                                    "Normal": {
                                        "Texture Path": "Ga_Skin_Body_Normal.png",
                                        "Strength": 100.0,
                                        "Offset": [
                                            0.0,
                                            0.0
                                        ],
                                        "Tiling": [
                                            1.0,
                                            1.0
                                        ]
                                    },
                                    "AO": {
                                        "Texture Path": "./textures/NPC_Aisha/NPC_Aisha/CC_Base_Body/Ga_Skin_Body/Ga_Skin_Body_ao.png",
                                        "Strength": 100.0,
                                        "Offset": [
                                            0.0,
                                            0.0
                                        ],
                                        "Tiling": [
                                            1.0,
                                            1.0
                                        ]
                                    },
                                    "MetallicAlpha": {
                                        "Texture Path": "./textures/NPC_Aisha/NPC_Aisha/CC_Base_Tongue/Ga_Skin_Body/Ga_Skin_Body_MetallicAlpha.png"
                                    },
                                    "HDRP": {
                                        "Texture Path": "./textures/NPC_Aisha/NPC_Aisha/CC_Base_Body/Ga_Skin_Body/Ga_Skin_Body_HDRP.png"
                                    }
                                },
                                "Resource Textures": {}
                            },
                            "Ga_Eyelash": {
                                "Material Type": "Pbr",
                                "MultiUV Index": 0,
                                "Two Side": true,
                                "Diffuse Color": [
                                    255.0,
                                    255.0,
                                    255.0
                                ],
                                "Ambient Color": [
                                    123.00000762939453,
                                    123.00000762939453,
                                    123.00000762939453
                                ],
                                "Specular Color": [
                                    229.5,
                                    229.5,
                                    229.5
                                ],
                                "Opacity": 1.0,
                                "Self Illumination": 0.0,
                                "Textures": {
                                    "Base Color": {
                                        "Texture Path": "Ga_Eyelash_Diffuse.png",
                                        "Strength": 100.0,
                                        "Offset": [
                                            0.0,
                                            0.0
                                        ],
                                        "Tiling": [
                                            1.0,
                                            1.0
                                        ]
                                    },
                                    "Roughness": {
                                        "Texture Path": "",
                                        "Strength": 100.0,
                                        "Offset": [
                                            0.0,
                                            0.0
                                        ],
                                        "Tiling": [
                                            1.0,
                                            1.0
                                        ]
                                    },
                                    "Opacity": {
                                        "Texture Path": "Ga_Eyelash_Diffuse.png",
                                        "Strength": 100.0,
                                        "Offset": [
                                            0.0,
                                            0.0
                                        ],
                                        "Tiling": [
                                            1.0,
                                            1.0
                                        ]
                                    },
                                    "Normal": {
                                        "Texture Path": "Ga_Eyelash_Normal.png",
                                        "Strength": 100.0,
                                        "Offset": [
                                            0.0,
                                            0.0
                                        ],
                                        "Tiling": [
                                            1.0,
                                            1.0
                                        ]
                                    },
                                    "AO": {
                                        "Texture Path": "./textures/NPC_Aisha/NPC_Aisha/CC_Base_Body/Ga_Eyelash/Ga_Eyelash_ao.png",
                                        "Strength": 100.0,
                                        "Offset": [
                                            0.0,
                                            0.0
                                        ],
                                        "Tiling": [
                                            1.0,
                                            1.0
                                        ]
                                    },
                                    "MetallicAlpha": {
                                        "Texture Path": "./textures/NPC_Aisha/NPC_Aisha/CC_Base_Body/Ga_Eyelash/Ga_Eyelash_MetallicAlpha.png"
                                    },
                                    "HDRP": {
                                        "Texture Path": "./textures/NPC_Aisha/NPC_Aisha/CC_Base_Body/Ga_Eyelash/Ga_Eyelash_HDRP.png"
                                    }
                                },
                                "Resource Textures": {}
                            }
                        }
                    },
                    "CC_Base_Tongue": {
                        "Materials": {
                            "Ga_Skin_Body": {
                                "Material Type": "Pbr",
                                "MultiUV Index": 0,
                                "Two Side": true,
                                "Diffuse Color": [
                                    255.0,
                                    255.0,
                                    255.0
                                ],
                                "Ambient Color": [
                                    254.00001525878907,
                                    254.00001525878907,
                                    254.00001525878907
                                ],
                                "Specular Color": [
                                    229.5,
                                    229.5,
                                    229.5
                                ],
                                "Opacity": 1.0,
                                "Self Illumination": 0.0,
                                "Textures": {
                                    "Metallic": {
                                        "Texture Path": "",
                                        "Strength": 100.0,
                                        "Offset": [
                                            0.0,
                                            0.0
                                        ],
                                        "Tiling": [
                                            1.0,
                                            1.0
                                        ]
                                    },
                                    "Base Color": {
                                        "Texture Path": "Ga_Skin_Body_Diffuse.png",
                                        "Strength": 100.0,
                                        "Offset": [
                                            0.0,
                                            0.0
                                        ],
                                        "Tiling": [
                                            1.0,
                                            1.0
                                        ]
                                    },
                                    "Roughness": {
                                        "Texture Path": "",
                                        "Strength": 100.0,
                                        "Offset": [
                                            0.0,
                                            0.0
                                        ],
                                        "Tiling": [
                                            1.0,
                                            1.0
                                        ]
                                    },
                                    "Normal": {
                                        "Texture Path": "Ga_Skin_Body_Normal.png",
                                        "Strength": 100.0,
                                        "Offset": [
                                            0.0,
                                            0.0
                                        ],
                                        "Tiling": [
                                            1.0,
                                            1.0
                                        ]
                                    },
                                    "AO": {
                                        "Texture Path": "./textures/NPC_Aisha/NPC_Aisha/CC_Base_Body/Ga_Skin_Body/Ga_Skin_Body_ao.png",
                                        "Strength": 100.0,
                                        "Offset": [
                                            0.0,
                                            0.0
                                        ],
                                        "Tiling": [
                                            1.0,
                                            1.0
                                        ]
                                    },
                                    "MetallicAlpha": {
                                        "Texture Path": "./textures/NPC_Aisha/NPC_Aisha/CC_Base_Tongue/Ga_Skin_Body/Ga_Skin_Body_MetallicAlpha.png"
                                    },
                                    "HDRP": {
                                        "Texture Path": "./textures/NPC_Aisha/NPC_Aisha/CC_Base_Body/Ga_Skin_Body/Ga_Skin_Body_HDRP.png"
                                    }
                                },
                                "Resource Textures": {}
                            },
                            "Ga_Eyelash": {
                                "Material Type": "Pbr",
                                "MultiUV Index": 0,
                                "Two Side": true,
                                "Diffuse Color": [
                                    255.0,
                                    255.0,
                                    255.0
                                ],
                                "Ambient Color": [
                                    123.00000762939453,
                                    123.00000762939453,
                                    123.00000762939453
                                ],
                                "Specular Color": [
                                    229.5,
                                    229.5,
                                    229.5
                                ],
                                "Opacity": 1.0,
                                "Self Illumination": 0.0,
                                "Textures": {
                                    "Base Color": {
                                        "Texture Path": "Ga_Eyelash_Diffuse.png",
                                        "Strength": 100.0,
                                        "Offset": [
                                            0.0,
                                            0.0
                                        ],
                                        "Tiling": [
                                            1.0,
                                            1.0
                                        ]
                                    },
                                    "Roughness": {
                                        "Texture Path": "",
                                        "Strength": 100.0,
                                        "Offset": [
                                            0.0,
                                            0.0
                                        ],
                                        "Tiling": [
                                            1.0,
                                            1.0
                                        ]
                                    },
                                    "Opacity": {
                                        "Texture Path": "Ga_Eyelash_Diffuse.png",
                                        "Strength": 100.0,
                                        "Offset": [
                                            0.0,
                                            0.0
                                        ],
                                        "Tiling": [
                                            1.0,
                                            1.0
                                        ]
                                    },
                                    "Normal": {
                                        "Texture Path": "Ga_Eyelash_Normal.png",
                                        "Strength": 100.0,
                                        "Offset": [
                                            0.0,
                                            0.0
                                        ],
                                        "Tiling": [
                                            1.0,
                                            1.0
                                        ]
                                    },
                                    "AO": {
                                        "Texture Path": "./textures/NPC_Aisha/NPC_Aisha/CC_Base_Body/Ga_Eyelash/Ga_Eyelash_ao.png",
                                        "Strength": 100.0,
                                        "Offset": [
                                            0.0,
                                            0.0
                                        ],
                                        "Tiling": [
                                            1.0,
                                            1.0
                                        ]
                                    },
                                    "MetallicAlpha": {
                                        "Texture Path": "./textures/NPC_Aisha/NPC_Aisha/CC_Base_Body/Ga_Eyelash/Ga_Eyelash_MetallicAlpha.png"
                                    },
                                    "HDRP": {
                                        "Texture Path": "./textures/NPC_Aisha/NPC_Aisha/CC_Base_Body/Ga_Eyelash/Ga_Eyelash_HDRP.png"
                                    }
                                },
                                "Resource Textures": {}
                            }
                        }
                    },
                    "Shoes": {
                        "Materials": {
                            "Shoes": {
                                "Material Type": "Pbr",
                                "MultiUV Index": 0,
                                "Two Side": true,
                                "Diffuse Color": [
                                    127.5,
                                    127.5,
                                    127.5
                                ],
                                "Ambient Color": [
                                    127.5,
                                    127.5,
                                    127.5
                                ],
                                "Specular Color": [
                                    0.0,
                                    0.0,
                                    0.0
                                ],
                                "Opacity": 1.0,
                                "Self Illumination": 0.0,
                                "Textures": {
                                    "Metallic": {
                                        "Texture Path": "",
                                        "Strength": 100.0,
                                        "Offset": [
                                            0.0,
                                            0.0
                                        ],
                                        "Tiling": [
                                            1.0,
                                            1.0
                                        ]
                                    },
                                    "Base Color": {
                                        "Texture Path": "Shoes_Diffuse.jpg",
                                        "Strength": 100.0,
                                        "Offset": [
                                            0.0,
                                            0.0
                                        ],
                                        "Tiling": [
                                            1.0,
                                            1.0
                                        ]
                                    },
                                    "Specular": {
                                        "Texture Path": "",
                                        "Strength": 100.0,
                                        "Offset": [
                                            0.0,
                                            0.0
                                        ],
                                        "Tiling": [
                                            1.0,
                                            1.0
                                        ]
                                    },
                                    "Roughness": {
                                        "Texture Path": "",
                                        "Strength": 100.0,
                                        "Offset": [
                                            0.0,
                                            0.0
                                        ],
                                        "Tiling": [
                                            1.0,
                                            1.0
                                        ]
                                    },
                                    "Normal": {
                                        "Texture Path": "Shoes_Normal.jpg",
                                        "Strength": 100.0,
                                        "Offset": [
                                            0.0,
                                            0.0
                                        ],
                                        "Tiling": [
                                            1.0,
                                            1.0
                                        ]
                                    },
                                    "AO": {
                                        "Texture Path": "./textures/NPC_Aisha/Shoes/Shoes/Shoes/Shoes_ao.png",
                                        "Strength": 100.0,
                                        "Offset": [
                                            0.0,
                                            0.0
                                        ],
                                        "Tiling": [
                                            1.0,
                                            1.0
                                        ]
                                    },
                                    "MetallicAlpha": {
                                        "Texture Path": "./textures/NPC_Aisha/Shoes/Shoes/Shoes/Shoes_MetallicAlpha.png"
                                    },
                                    "HDRP": {
                                        "Texture Path": "./textures/NPC_Aisha/Shoes/Shoes/Shoes/Shoes_HDRP.png"
                                    }
                                },
                                "Resource Textures": {}
                            }
                        }
                    },
                    "Sash": {
                        "Materials": {
                            "Sash": {
                                "Material Type": "Pbr",
                                "MultiUV Index": 0,
                                "Two Side": true,
                                "Diffuse Color": [
                                    127.5,
                                    127.5,
                                    127.5
                                ],
                                "Ambient Color": [
                                    127.5,
                                    127.5,
                                    127.5
                                ],
                                "Specular Color": [
                                    0.0,
                                    0.0,
                                    0.0
                                ],
                                "Opacity": 1.0,
                                "Self Illumination": 0.0,
                                "Textures": {
                                    "Metallic": {
                                        "Texture Path": "",
                                        "Strength": 100.0,
                                        "Offset": [
                                            0.0,
                                            0.0
                                        ],
                                        "Tiling": [
                                            1.0,
                                            1.0
                                        ]
                                    },
                                    "Base Color": {
                                        "Texture Path": "Sash_Diffuse.jpg",
                                        "Strength": 100.0,
                                        "Offset": [
                                            0.0,
                                            0.0
                                        ],
                                        "Tiling": [
                                            1.0,
                                            1.0
                                        ]
                                    },
                                    "Specular": {
                                        "Texture Path": "",
                                        "Strength": 100.0,
                                        "Offset": [
                                            0.0,
                                            0.0
                                        ],
                                        "Tiling": [
                                            1.0,
                                            1.0
                                        ]
                                    },
                                    "Roughness": {
                                        "Texture Path": "",
                                        "Strength": 100.0,
                                        "Offset": [
                                            0.0,
                                            0.0
                                        ],
                                        "Tiling": [
                                            1.0,
                                            1.0
                                        ]
                                    },
                                    "Normal": {
                                        "Texture Path": "Sash_Normal.jpg",
                                        "Strength": 100.0,
                                        "Offset": [
                                            0.0,
                                            0.0
                                        ],
                                        "Tiling": [
                                            1.0,
                                            1.0
                                        ]
                                    },
                                    "AO": {
                                        "Texture Path": "./textures/NPC_Aisha/Sash/Sash/Sash/Sash_ao.png",
                                        "Strength": 100.0,
                                        "Offset": [
                                            0.0,
                                            0.0
                                        ],
                                        "Tiling": [
                                            1.0,
                                            1.0
                                        ]
                                    },
                                    "MetallicAlpha": {
                                        "Texture Path": "./textures/NPC_Aisha/Sash/Sash/Sash/Sash_MetallicAlpha.png"
                                    },
                                    "HDRP": {
                                        "Texture Path": "./textures/NPC_Aisha/Sash/Sash/Sash/Sash_HDRP.png"
                                    }
                                },
                                "Resource Textures": {}
                            }
                        }
                    },
                    "Robe_Long_01": {
                        "Materials": {
                            "Robe_Long_01": {
                                "Material Type": "Pbr",
                                "MultiUV Index": 0,
                                "Two Side": true,
                                "Diffuse Color": [
                                    127.5,
                                    127.5,
                                    127.5
                                ],
                                "Ambient Color": [
                                    127.5,
                                    127.5,
                                    127.5
                                ],
                                "Specular Color": [
                                    0.0,
                                    0.0,
                                    0.0
                                ],
                                "Opacity": 1.0,
                                "Self Illumination": 0.0,
                                "Textures": {
                                    "Metallic": {
                                        "Texture Path": "",
                                        "Strength": 100.0,
                                        "Offset": [
                                            0.0,
                                            0.0
                                        ],
                                        "Tiling": [
                                            1.0,
                                            1.0
                                        ]
                                    },
                                    "Base Color": {
                                        "Texture Path": "Robe_Long_01_Diffuse.jpg",
                                        "Strength": 100.0,
                                        "Offset": [
                                            0.0,
                                            0.0
                                        ],
                                        "Tiling": [
                                            1.0,
                                            1.0
                                        ]
                                    },
                                    "Specular": {
                                        "Texture Path": "",
                                        "Strength": 100.0,
                                        "Offset": [
                                            0.0,
                                            0.0
                                        ],
                                        "Tiling": [
                                            1.0,
                                            1.0
                                        ]
                                    },
                                    "Roughness": {
                                        "Texture Path": "",
                                        "Strength": 100.0,
                                        "Offset": [
                                            0.0,
                                            0.0
                                        ],
                                        "Tiling": [
                                            1.0,
                                            1.0
                                        ]
                                    },
                                    "Normal": {
                                        "Texture Path": "Robe_Long_01_Normal.jpg",
                                        "Strength": 100.0,
                                        "Offset": [
                                            0.0,
                                            0.0
                                        ],
                                        "Tiling": [
                                            1.0,
                                            1.0
                                        ]
                                    },
                                    "AO": {
                                        "Texture Path": "./textures/NPC_Aisha/Robe_Long_01/Robe_Long_01/Robe_Long_01/Robe_Long_01_ao.png",
                                        "Strength": 100.0,
                                        "Offset": [
                                            0.0,
                                            0.0
                                        ],
                                        "Tiling": [
                                            1.0,
                                            1.0
                                        ]
                                    },
                                    "MetallicAlpha": {
                                        "Texture Path": "./textures/NPC_Aisha/Robe_Long_01/Robe_Long_01/Robe_Long_01/Robe_Long_01_MetallicAlpha.png"
                                    },
                                    "HDRP": {
                                        "Texture Path": "./textures/NPC_Aisha/Robe_Long_01/Robe_Long_01/Robe_Long_01/Robe_Long_01_HDRP.png"
                                    }
                                },
                                "Resource Textures": {}
                            }
                        }
                    },
                    "Coat_Short": {
                        "Materials": {
                            "Coat_Short": {
                                "Material Type": "Pbr",
                                "MultiUV Index": 0,
                                "Two Side": true,
                                "Diffuse Color": [
                                    127.5,
                                    127.5,
                                    127.5
                                ],
                                "Ambient Color": [
                                    127.5,
                                    127.5,
                                    127.5
                                ],
                                "Specular Color": [
                                    0.0,
                                    0.0,
                                    0.0
                                ],
                                "Opacity": 1.0,
                                "Self Illumination": 0.0,
                                "Textures": {
                                    "Metallic": {
                                        "Texture Path": "",
                                        "Strength": 100.0,
                                        "Offset": [
                                            0.0,
                                            0.0
                                        ],
                                        "Tiling": [
                                            1.0,
                                            1.0
                                        ]
                                    },
                                    "Base Color": {
                                        "Texture Path": "Coat_Short_Diffuse.jpg",
                                        "Strength": 100.0,
                                        "Offset": [
                                            0.0,
                                            0.0
                                        ],
                                        "Tiling": [
                                            1.0,
                                            1.0
                                        ]
                                    },
                                    "Specular": {
                                        "Texture Path": "",
                                        "Strength": 100.0,
                                        "Offset": [
                                            0.0,
                                            0.0
                                        ],
                                        "Tiling": [
                                            1.0,
                                            1.0
                                        ]
                                    },
                                    "Roughness": {
                                        "Texture Path": "",
                                        "Strength": 100.0,
                                        "Offset": [
                                            0.0,
                                            0.0
                                        ],
                                        "Tiling": [
                                            1.0,
                                            1.0
                                        ]
                                    },
                                    "Normal": {
                                        "Texture Path": "Coat_Short_Normal.jpg",
                                        "Strength": 100.0,
                                        "Offset": [
                                            0.0,
                                            0.0
                                        ],
                                        "Tiling": [
                                            1.0,
                                            1.0
                                        ]
                                    },
                                    "AO": {
                                        "Texture Path": "./textures/NPC_Aisha/Coat_Short/Coat_Short/Coat_Short/Coat_Short_ao.png",
                                        "Strength": 100.0,
                                        "Offset": [
                                            0.0,
                                            0.0
                                        ],
                                        "Tiling": [
                                            1.0,
                                            1.0
                                        ]
                                    },
                                    "MetallicAlpha": {
                                        "Texture Path": "./textures/NPC_Aisha/Coat_Short/Coat_Short/Coat_Short/Coat_Short_MetallicAlpha.png"
                                    },
                                    "HDRP": {
                                        "Texture Path": "./textures/NPC_Aisha/Coat_Short/Coat_Short/Coat_Short/Coat_Short_HDRP.png"
                                    }
                                },
                                "Resource Textures": {}
                            }
                        }
                    },
                    "Cloth_Hood_01": {
                        "Materials": {
                            "Cloth_Hood_01": {
                                "Material Type": "Pbr",
                                "MultiUV Index": 0,
                                "Two Side": true,
                                "Diffuse Color": [
                                    127.5,
                                    127.5,
                                    127.5
                                ],
                                "Ambient Color": [
                                    127.5,
                                    127.5,
                                    127.5
                                ],
                                "Specular Color": [
                                    0.0,
                                    0.0,
                                    0.0
                                ],
                                "Opacity": 1.0,
                                "Self Illumination": 0.0,
                                "Textures": {
                                    "Metallic": {
                                        "Texture Path": "",
                                        "Strength": 100.0,
                                        "Offset": [
                                            0.0,
                                            0.0
                                        ],
                                        "Tiling": [
                                            1.0,
                                            1.0
                                        ]
                                    },
                                    "Base Color": {
                                        "Texture Path": "Cloth_Hood_01_Diffuse.jpg",
                                        "Strength": 100.0,
                                        "Offset": [
                                            0.0,
                                            0.0
                                        ],
                                        "Tiling": [
                                            1.0,
                                            1.0
                                        ]
                                    },
                                    "Specular": {
                                        "Texture Path": "",
                                        "Strength": 100.0,
                                        "Offset": [
                                            0.0,
                                            0.0
                                        ],
                                        "Tiling": [
                                            1.0,
                                            1.0
                                        ]
                                    },
                                    "Roughness": {
                                        "Texture Path": "",
                                        "Strength": 100.0,
                                        "Offset": [
                                            0.0,
                                            0.0
                                        ],
                                        "Tiling": [
                                            1.0,
                                            1.0
                                        ]
                                    },
                                    "Normal": {
                                        "Texture Path": "Cloth_Hood_01_Normal.jpg",
                                        "Strength": 100.0,
                                        "Offset": [
                                            0.0,
                                            0.0
                                        ],
                                        "Tiling": [
                                            1.0,
                                            1.0
                                        ]
                                    },
                                    "AO": {
                                        "Texture Path": "./textures/NPC_Aisha/Cloth_Hood_01/Cloth_Hood_01/Cloth_Hood_01/Cloth_Hood_01_ao.png",
                                        "Strength": 100.0,
                                        "Offset": [
                                            0.0,
                                            0.0
                                        ],
                                        "Tiling": [
                                            1.0,
                                            1.0
                                        ]
                                    },
                                    "MetallicAlpha": {
                                        "Texture Path": "./textures/NPC_Aisha/Cloth_Hood_01/Cloth_Hood_01/Cloth_Hood_01/Cloth_Hood_01_MetallicAlpha.png"
                                    },
                                    "HDRP": {
                                        "Texture Path": "./textures/NPC_Aisha/Cloth_Hood_01/Cloth_Hood_01/Cloth_Hood_01/Cloth_Hood_01_HDRP.png"
                                    }
                                },
                                "Resource Textures": {}
                            }
                        }
                    },
                    "CC_Base_Eye": {
                        "Materials": {
                            "Std_Eye_R": {
                                "Material Type": "Pbr",
                                "MultiUV Index": 0,
                                "Two Side": false,
                                "Diffuse Color": [
                                    255.0,
                                    255.0,
                                    255.0
                                ],
                                "Ambient Color": [
                                    50.000003814697269,
                                    50.000003814697269,
                                    50.000003814697269
                                ],
                                "Specular Color": [
                                    229.00001525878907,
                                    229.00001525878907,
                                    229.00001525878907
                                ],
                                "Opacity": 1.0,
                                "Self Illumination": 0.0,
                                "Textures": {
                                    "Metallic": {
                                        "Texture Path": "",
                                        "Strength": 100.0,
                                        "Offset": [
                                            0.0,
                                            0.0
                                        ],
                                        "Tiling": [
                                            1.0,
                                            1.0
                                        ]
                                    },
                                    "Base Color": {
                                        "Texture Path": "Std_Eye_R_Diffuse.jpg",
                                        "Strength": 100.0,
                                        "Offset": [
                                            0.0,
                                            0.0
                                        ],
                                        "Tiling": [
                                            1.0,
                                            1.0
                                        ]
                                    },
                                    "Roughness": {
                                        "Texture Path": "",
                                        "Strength": 100.0,
                                        "Offset": [
                                            0.0,
                                            0.0
                                        ],
                                        "Tiling": [
                                            1.0,
                                            1.0
                                        ]
                                    },
                                    "Normal": {
                                        "Texture Path": "Std_Eye_R_Normal.png",
                                        "Strength": 100.0,
                                        "Offset": [
                                            0.0,
                                            0.0
                                        ],
                                        "Tiling": [
                                            1.0,
                                            1.0
                                        ]
                                    },
                                    "MetallicAlpha": {
                                        "Texture Path": "./textures/NPC_Aisha/CC_Base_Eye/CC_Base_Eye/Std_Eye_R/Std_Eye_R_MetallicAlpha.png"
                                    },
                                    "HDRP": {
                                        "Texture Path": "./textures/NPC_Aisha/CC_Base_Eye/CC_Base_Eye/Std_Eye_R/Std_Eye_R_HDRP.png"
                                    }
                                },
                                "Resource Textures": {}
                            },
                            "Std_Cornea_R": {
                                "Material Type": "Pbr",
                                "MultiUV Index": 0,
                                "Two Side": false,
                                "Diffuse Color": [
                                    255.0,
                                    255.0,
                                    255.0
                                ],
                                "Ambient Color": [
                                    50.000003814697269,
                                    50.000003814697269,
                                    50.000003814697269
                                ],
                                "Specular Color": [
                                    0.0,
                                    0.0,
                                    0.0
                                ],
                                "Opacity": 0.800000011920929,
                                "Self Illumination": 0.0,
                                "Textures": {
                                    "Metallic": {
                                        "Texture Path": "",
                                        "Strength": 100.0,
                                        "Offset": [
                                            0.0,
                                            0.0
                                        ],
                                        "Tiling": [
                                            1.0,
                                            1.0
                                        ]
                                    },
                                    "Base Color": {
                                        "Texture Path": "Std_Cornea_R_Diffuse.jpg",
                                        "Strength": 100.0,
                                        "Offset": [
                                            0.0,
                                            0.0
                                        ],
                                        "Tiling": [
                                            1.0,
                                            1.0
                                        ]
                                    },
                                    "Roughness": {
                                        "Texture Path": "",
                                        "Strength": 100.0,
                                        "Offset": [
                                            0.0,
                                            0.0
                                        ],
                                        "Tiling": [
                                            1.0,
                                            1.0
                                        ]
                                    },
                                    "AO": {
                                        "Texture Path": "./textures/NPC_Aisha/CC_Base_Eye/CC_Base_Eye/Std_Cornea_R/Std_Cornea_R_ao.png",
                                        "Strength": 50.0,
                                        "Offset": [
                                            0.0,
                                            0.0
                                        ],
                                        "Tiling": [
                                            1.0,
                                            1.0
                                        ]
                                    },
                                    "MetallicAlpha": {
                                        "Texture Path": "./textures/NPC_Aisha/CC_Base_Eye/CC_Base_Eye/Std_Cornea_R/Std_Cornea_R_MetallicAlpha.png"
                                    },
                                    "HDRP": {
                                        "Texture Path": "./textures/NPC_Aisha/CC_Base_Eye/CC_Base_Eye/Std_Cornea_R/Std_Cornea_R_HDRP.png"
                                    }
                                },
                                "Resource Textures": {},
                                "Custom Shader": {
                                    "Shader Name": "RLEye",
                                    "Image": {
                                        "Iris Normal": {
                                            "Texture Path": "./textures/NPC_Aisha/CC_Base_Eye/CC_Base_Eye/Std_Cornea_R/Std_Cornea_R_IrisN.png"
                                        },
                                        "Sclera Normal": {
                                            "Texture Path": "./textures/NPC_Aisha/CC_Base_Eye/CC_Base_Eye/Std_Cornea_R/Std_Cornea_R_ScleraN.png"
                                        },
                                        "EyeBlendMap2": {
                                            "Texture Path": "./textures/NPC_Aisha/CC_Base_Eye/CC_Base_Eye/Std_Cornea_R/Std_Cornea_R_BCBMap.jpg"
                                        },
                                        "Inner Iris Mask": {
                                            "Texture Path": "./textures/NPC_Aisha/CC_Base_Eye/CC_Base_Eye/Std_Cornea_R/Std_Cornea_R_IrisMask.png"
                                        },
                                        "Sclera": {
                                            "Texture Path": "./textures/NPC_Aisha/CC_Base_Eye/CC_Base_Eye/Std_Cornea_R/Std_Cornea_R_Sclera.jpg"
                                        }
                                    },
                                    "Variable": {
                                        "BlendMap2 Strength": 0.0,
                                        "Shadow Radius": 0.4000000059604645,
                                        "Shadow Hardness": 0.5,
                                        "Specular Scale": 0.800000011920929,
                                        "Is Left Eye": 1.0,
                                        "Eye Corner Darkness Color": [
                                            255.0,
                                            187.9860076904297,
                                            178.9998016357422
                                        ],
                                        "Iris Depth Scale": 0.8999999761581421,
                                        "_Iris Roughness": 0.0,
                                        "Iris Color Brightness": 1.0,
                                        "Pupil Scale": 0.9549999833106995,
                                        "_IoR": 1.399999976158142,
                                        "Iris Cloudy Color": [
                                            0.0,
                                            2.549999952316284,
                                            2.549999952316284
                                        ],
                                        "Iris Inner Color": [
                                            255.0,
                                            223.0,
                                            125.0
                                        ],
                                        "Iris Inner Scale": 0.0,
                                        "Iris UV Radius": 0.1599999964237213,
                                        "Iris Color": [
                                            255.0,
                                            255.0,
                                            255.0
                                        ],
                                        "Limbus UV Width Color": 0.04500000178813934,
                                        "Limbus Dark Scale": 6.5,
                                        "ScleraBrightness": 0.6499999761581421,
                                        "Sclera Roughness": 0.20000000298023225,
                                        "Sclera Flatten Normal": 0.8999999761581421,
                                        "Sclera Normal UV Scale": 0.5,
                                        "Sclera UV Radius": 0.9300000071525574
                                    }
                                },
                                "Subsurface Scatter": {
                                    "Falloff": [
                                        255.0,
                                        255.0,
                                        255.0
                                    ],
                                    "Radius": 5.0,
                                    "Distribution": 0.9300000071525574,
                                    "IOR": 1.5499999523162842,
                                    "DecayScale": 1.0,
                                    "Lerp": 0.8500000238418579
                                }
                            },
                            "Std_Eye_L": {
                                "Material Type": "Pbr",
                                "MultiUV Index": 0,
                                "Two Side": false,
                                "Diffuse Color": [
                                    255.0,
                                    255.0,
                                    255.0
                                ],
                                "Ambient Color": [
                                    50.000003814697269,
                                    50.000003814697269,
                                    50.000003814697269
                                ],
                                "Specular Color": [
                                    229.00001525878907,
                                    229.00001525878907,
                                    229.00001525878907
                                ],
                                "Opacity": 1.0,
                                "Self Illumination": 0.0,
                                "Textures": {
                                    "Metallic": {
                                        "Texture Path": "",
                                        "Strength": 100.0,
                                        "Offset": [
                                            0.0,
                                            0.0
                                        ],
                                        "Tiling": [
                                            1.0,
                                            1.0
                                        ]
                                    },
                                    "Base Color": {
                                        "Texture Path": "Std_Eye_L_Diffuse.jpg",
                                        "Strength": 100.0,
                                        "Offset": [
                                            0.0,
                                            0.0
                                        ],
                                        "Tiling": [
                                            1.0,
                                            1.0
                                        ]
                                    },
                                    "Roughness": {
                                        "Texture Path": "",
                                        "Strength": 100.0,
                                        "Offset": [
                                            0.0,
                                            0.0
                                        ],
                                        "Tiling": [
                                            1.0,
                                            1.0
                                        ]
                                    },
                                    "Normal": {
                                        "Texture Path": "Std_Eye_L_Normal.png",
                                        "Strength": 100.0,
                                        "Offset": [
                                            0.0,
                                            0.0
                                        ],
                                        "Tiling": [
                                            1.0,
                                            1.0
                                        ]
                                    },
                                    "MetallicAlpha": {
                                        "Texture Path": "./textures/NPC_Aisha/CC_Base_Eye/CC_Base_Eye/Std_Eye_L/Std_Eye_L_MetallicAlpha.png"
                                    },
                                    "HDRP": {
                                        "Texture Path": "./textures/NPC_Aisha/CC_Base_Eye/CC_Base_Eye/Std_Eye_L/Std_Eye_L_HDRP.png"
                                    }
                                },
                                "Resource Textures": {}
                            },
                            "Std_Cornea_L": {
                                "Material Type": "Pbr",
                                "MultiUV Index": 0,
                                "Two Side": false,
                                "Diffuse Color": [
                                    255.0,
                                    255.0,
                                    255.0
                                ],
                                "Ambient Color": [
                                    50.000003814697269,
                                    50.000003814697269,
                                    50.000003814697269
                                ],
                                "Specular Color": [
                                    0.0,
                                    0.0,
                                    0.0
                                ],
                                "Opacity": 0.800000011920929,
                                "Self Illumination": 0.0,
                                "Textures": {
                                    "Metallic": {
                                        "Texture Path": "",
                                        "Strength": 100.0,
                                        "Offset": [
                                            0.0,
                                            0.0
                                        ],
                                        "Tiling": [
                                            1.0,
                                            1.0
                                        ]
                                    },
                                    "Base Color": {
                                        "Texture Path": "Std_Cornea_L_Diffuse.jpg",
                                        "Strength": 100.0,
                                        "Offset": [
                                            0.0,
                                            0.0
                                        ],
                                        "Tiling": [
                                            1.0,
                                            1.0
                                        ]
                                    },
                                    "Roughness": {
                                        "Texture Path": "",
                                        "Strength": 100.0,
                                        "Offset": [
                                            0.0,
                                            0.0
                                        ],
                                        "Tiling": [
                                            1.0,
                                            1.0
                                        ]
                                    },
                                    "AO": {
                                        "Texture Path": "./textures/NPC_Aisha/CC_Base_Eye/CC_Base_Eye/Std_Cornea_L/Std_Cornea_L_ao.png",
                                        "Strength": 50.0,
                                        "Offset": [
                                            0.0,
                                            0.0
                                        ],
                                        "Tiling": [
                                            1.0,
                                            1.0
                                        ]
                                    },
                                    "MetallicAlpha": {
                                        "Texture Path": "./textures/NPC_Aisha/CC_Base_Eye/CC_Base_Eye/Std_Cornea_L/Std_Cornea_L_MetallicAlpha.png"
                                    },
                                    "HDRP": {
                                        "Texture Path": "./textures/NPC_Aisha/CC_Base_Eye/CC_Base_Eye/Std_Cornea_L/Std_Cornea_L_HDRP.png"
                                    }
                                },
                                "Resource Textures": {},
                                "Custom Shader": {
                                    "Shader Name": "RLEye",
                                    "Image": {
                                        "Iris Normal": {
                                            "Texture Path": "./textures/NPC_Aisha/CC_Base_Eye/CC_Base_Eye/Std_Cornea_R/Std_Cornea_R_IrisN.png"
                                        },
                                        "Sclera Normal": {
                                            "Texture Path": "./textures/NPC_Aisha/CC_Base_Eye/CC_Base_Eye/Std_Cornea_R/Std_Cornea_R_ScleraN.png"
                                        },
                                        "EyeBlendMap2": {
                                            "Texture Path": "./textures/NPC_Aisha/CC_Base_Eye/CC_Base_Eye/Std_Cornea_R/Std_Cornea_R_BCBMap.jpg"
                                        },
                                        "Inner Iris Mask": {
                                            "Texture Path": "./textures/NPC_Aisha/CC_Base_Eye/CC_Base_Eye/Std_Cornea_R/Std_Cornea_R_IrisMask.png"
                                        },
                                        "Sclera": {
                                            "Texture Path": "./textures/NPC_Aisha/CC_Base_Eye/CC_Base_Eye/Std_Cornea_R/Std_Cornea_R_Sclera.jpg"
                                        }
                                    },
                                    "Variable": {
                                        "BlendMap2 Strength": 0.0,
                                        "Shadow Radius": 0.4000000059604645,
                                        "Shadow Hardness": 0.5,
                                        "Specular Scale": 0.800000011920929,
                                        "Is Left Eye": 1.0,
                                        "Eye Corner Darkness Color": [
                                            255.0,
                                            187.9860076904297,
                                            178.9998016357422
                                        ],
                                        "Iris Depth Scale": 0.8999999761581421,
                                        "_Iris Roughness": 0.0,
                                        "Iris Color Brightness": 1.0,
                                        "Pupil Scale": 0.9549999833106995,
                                        "_IoR": 1.399999976158142,
                                        "Iris Cloudy Color": [
                                            0.0,
                                            2.549999952316284,
                                            2.549999952316284
                                        ],
                                        "Iris Inner Color": [
                                            255.0,
                                            223.0,
                                            125.0
                                        ],
                                        "Iris Inner Scale": 0.0,
                                        "Iris UV Radius": 0.1599999964237213,
                                        "Iris Color": [
                                            255.0,
                                            255.0,
                                            255.0
                                        ],
                                        "Limbus UV Width Color": 0.04500000178813934,
                                        "Limbus Dark Scale": 6.5,
                                        "ScleraBrightness": 0.6499999761581421,
                                        "Sclera Roughness": 0.20000000298023225,
                                        "Sclera Flatten Normal": 0.8999999761581421,
                                        "Sclera Normal UV Scale": 0.5,
                                        "Sclera UV Radius": 0.9300000071525574
                                    }
                                },
                                "Subsurface Scatter": {
                                    "Falloff": [
                                        255.0,
                                        255.0,
                                        255.0
                                    ],
                                    "Radius": 5.0,
                                    "Distribution": 0.9300000071525574,
                                    "IOR": 1.5499999523162842,
                                    "DecayScale": 1.0,
                                    "Lerp": 0.8500000238418579
                                }
                            }
                        }
                    },
                    "CC_Game_Teeth": {
                        "Materials": {
                            "Ga_Teeth": {
                                "Material Type": "Pbr",
                                "MultiUV Index": 0,
                                "Two Side": false,
                                "Diffuse Color": [
                                    255.0,
                                    255.0,
                                    255.0
                                ],
                                "Ambient Color": [
                                    255.0,
                                    255.0,
                                    255.0
                                ],
                                "Specular Color": [
                                    229.5,
                                    229.5,
                                    229.5
                                ],
                                "Opacity": 1.0,
                                "Self Illumination": 0.0,
                                "Textures": {
                                    "Metallic": {
                                        "Texture Path": "",
                                        "Strength": 100.0,
                                        "Offset": [
                                            0.0,
                                            0.0
                                        ],
                                        "Tiling": [
                                            1.0,
                                            1.0
                                        ]
                                    },
                                    "Base Color": {
                                        "Texture Path": "Ga_Teeth_Diffuse.jpg",
                                        "Strength": 100.0,
                                        "Offset": [
                                            0.0,
                                            0.0
                                        ],
                                        "Tiling": [
                                            1.0,
                                            1.0
                                        ]
                                    },
                                    "Roughness": {
                                        "Texture Path": "",
                                        "Strength": 100.0,
                                        "Offset": [
                                            0.0,
                                            0.0
                                        ],
                                        "Tiling": [
                                            1.0,
                                            1.0
                                        ]
                                    },
                                    "Normal": {
                                        "Texture Path": "Ga_Teeth_Normal.jpg",
                                        "Strength": 100.0,
                                        "Offset": [
                                            0.0,
                                            0.0
                                        ],
                                        "Tiling": [
                                            1.0,
                                            1.0
                                        ]
                                    },
                                    "AO": {
                                        "Texture Path": "./textures/NPC_Aisha/CC_Game_Teeth/CC_Game_Teeth/Ga_Teeth/Ga_Teeth_ao.png",
                                        "Strength": 100.0,
                                        "Offset": [
                                            0.0,
                                            0.0
                                        ],
                                        "Tiling": [
                                            1.0,
                                            1.0
                                        ]
                                    },
                                    "MetallicAlpha": {
                                        "Texture Path": "./textures/NPC_Aisha/CC_Game_Teeth/CC_Game_Teeth/Ga_Teeth/Ga_Teeth_MetallicAlpha.png"
                                    },
                                    "HDRP": {
                                        "Texture Path": "./textures/NPC_Aisha/CC_Game_Teeth/CC_Game_Teeth/Ga_Teeth/Ga_Teeth_HDRP.png"
                                    }
                                },
                                "Resource Textures": {}
                            }
                        }
                    }
                }
            }
        }
    }
}